tentapp
