Metadata-Version: 1.0
Name: tentapp
Version: 0.1.0dev3
Summary: Python client/app library for the Tent protocol (https://tent.io)
Home-page: https://github.com/longears/python-tent-client/
Author: David Wallace
Author-email: david.wallace+tentapp@gmail.com
License: MIT License
Platform: UNKNOWN
Classifier: Development Status :: 3 - Alpha
Classifier: Intended Audience :: Developers
Classifier: License :: OSI Approved :: MIT License
Classifier: Operating System :: OS Independent
Classifier: Programming Language :: Python :: 2.7
Classifier: Programming Language :: Python
Classifier: Topic :: Communications
Classifier: Topic :: Internet
Classifier: Topic :: Software Development :: Libraries :: Python Modules
